.gitignore
CHANGES.rst
LICENSE.txt
README.rst
bootstrap.py
buildout.cfg
setup.py
js/__init__.py
js.jquery_scrolltofixed.egg-info/PKG-INFO
js.jquery_scrolltofixed.egg-info/SOURCES.txt
js.jquery_scrolltofixed.egg-info/dependency_links.txt
js.jquery_scrolltofixed.egg-info/entry_points.txt
js.jquery_scrolltofixed.egg-info/namespace_packages.txt
js.jquery_scrolltofixed.egg-info/not-zip-safe
js.jquery_scrolltofixed.egg-info/requires.txt
js.jquery_scrolltofixed.egg-info/top_level.txt
js/jquery_scrolltofixed/__init__.py
js/jquery_scrolltofixed/test_scrolltofixed.txt
js/jquery_scrolltofixed/resources/jquery-scrolltofixed-min.js
js/jquery_scrolltofixed/resources/jquery-scrolltofixed.js