Metadata-Version: 1.0
Name: js.jquery-scrolltofixed
Version: 0.1
Summary: Fanstatic packaging of ScrollToFixed (jQuery plugin)
Home-page: UNKNOWN
Author: Fanstatic Developers
Author-email: fanstatic@googlegroups.com
License: BSD
Platform: UNKNOWN
